ddebug/LICENSE
ddebug/__init__.py
ddebug/dd_class.py
ddebug/dd_util.py
ddebug/richlib.py
ddebug/watchlib.py
ddebug-0.4.7.dist-info/WHEEL
ddebug-0.4.7.dist-info/METADATA
ddebug-0.4.7.dist-info/RECORD
