Metadata-Version: 2.1
Name: ddebug
Version: 0.4.7
Summary: python library with a set of tools for simple debugging of python programs
Home-page: https://github.com/matan-h/ddebug
License: MIT
Keywords: ddebug,debug,simple,quick,easy,dd,debuging
Author: matan h
Author-email: matan.honig2@gmail.com
Requires-Python: >=3.6,<4.0
Classifier: License :: OSI Approved :: MIT License
Classifier: Programming Language :: Python :: 3
Classifier: Programming Language :: Python :: 3.10
Classifier: Programming Language :: Python :: 3.6
Classifier: Programming Language :: Python :: 3.7
Classifier: Programming Language :: Python :: 3.8
Classifier: Programming Language :: Python :: 3.9
Provides-Extra: full
Provides-Extra: no-pdbr
Requires-Dist: deepdiff (>=5.0.0,<6.0.0); extra == "full"
Requires-Dist: friendly-traceback (>=0.3.150,<0.4.0)
Requires-Dist: icecream (>=2.1.0,<3.0.0)
Requires-Dist: inputimeout (>=1.0.0,<2.0.0); extra == "full"
Requires-Dist: pdbr (>=0.5.2,<0.6.0); extra == "full"
Requires-Dist: rich (>=10.5.0,<11.0.0)
Requires-Dist: snoop (>=0.3,<0.5)
Requires-Dist: watchpoints (>=0.1.3,<0.3.0); extra == "full" or extra == "no-pdbr"
Project-URL: issues, https://github.com/matan-h/ddebug/issues
